<annotation>
	<folder>image</folder>
	<filename>car-wbs-HR99BJ6662_00000.jpeg</filename>
	<path>C:\Users\Siri\Desktop\BARC_ki_padhai\Project\Indian_ANPR_090921\v3andv4\image\car-wbs-HR99BJ6662_00000.jpeg</path>
	<source>
		<database>Unknown</database>
	</source>
	<size>
		<width>919</width>
		<height>532</height>
		<depth>3</depth>
	</size>
	<segmented>0</segmented>
	<object>
		<name>HR99BJ6662</name>
		<pose>Unspecified</pose>
		<truncated>0</truncated>
		<difficult>0</difficult>
		<bndbox>
			<xmin>260</xmin>
			<ymin>203</ymin>
			<xmax>730</xmax>
			<ymax>346</ymax>
		</bndbox>
	</object>
</annotation>
