<annotation>
	<folder>CH</folder>
	<filename>CH3.jpg</filename>
	<path>C:\Users\Siri\Downloads\OLX_images\CH\CH3.jpg</path>
	<source>
		<database>Unknown</database>
	</source>
	<size>
		<width>272</width>
		<height>363</height>
		<depth>3</depth>
	</size>
	<segmented>0</segmented>
	<object>
		<name>CH03K7672</name>
		<pose>Unspecified</pose>
		<truncated>0</truncated>
		<difficult>0</difficult>
		<bndbox>
			<xmin>55</xmin>
			<ymin>270</ymin>
			<xmax>144</xmax>
			<ymax>291</ymax>
		</bndbox>
	</object>
</annotation>
