<annotation>
	<folder>PB</folder>
	<filename>PB21.jpg</filename>
	<path>C:\Users\Siri\Downloads\OLX_images\PB\PB21.jpg</path>
	<source>
		<database>Unknown</database>
	</source>
	<size>
		<width>272</width>
		<height>581</height>
		<depth>3</depth>
	</size>
	<segmented>0</segmented>
	<object>
		<name>PB37A8269</name>
		<pose>Unspecified</pose>
		<truncated>0</truncated>
		<difficult>0</difficult>
		<bndbox>
			<xmin>72</xmin>
			<ymin>363</ymin>
			<xmax>168</xmax>
			<ymax>396</ymax>
		</bndbox>
	</object>
</annotation>
